README
iiif-validate.py
iiif-validator.py
setup.py
iiif_validator/__init__.py
iiif_validator/_version.py
iiif_validator/apache.py
iiif_validator/validator.py
iiif_validator.egg-info/PKG-INFO
iiif_validator.egg-info/SOURCES.txt
iiif_validator.egg-info/dependency_links.txt
iiif_validator.egg-info/requires.txt
iiif_validator.egg-info/top_level.txt
iiif_validator/tests/__init__.py
iiif_validator/tests/baseurl_redirect.py
iiif_validator/tests/cors.py
iiif_validator/tests/format_conneg.py
iiif_validator/tests/format_error_random.py
iiif_validator/tests/format_gif.py
iiif_validator/tests/format_jp2.py
iiif_validator/tests/format_jpg.py
iiif_validator/tests/format_pdf.py
iiif_validator/tests/format_png.py
iiif_validator/tests/format_tif.py
iiif_validator/tests/format_webp.py
iiif_validator/tests/id_basic.py
iiif_validator/tests/id_error_escapedslash.py
iiif_validator/tests/id_error_random.py
iiif_validator/tests/id_error_unescaped.py
iiif_validator/tests/id_escaped.py
iiif_validator/tests/id_squares.py
iiif_validator/tests/info_json.py
iiif_validator/tests/info_xml.py
iiif_validator/tests/jsonld.py
iiif_validator/tests/linkheader_canonical.py
iiif_validator/tests/linkheader_profile.py
iiif_validator/tests/quality_bitonal.py
iiif_validator/tests/quality_color.py
iiif_validator/tests/quality_error_random.py
iiif_validator/tests/quality_grey.py
iiif_validator/tests/region_error_random.py
iiif_validator/tests/region_percent.py
iiif_validator/tests/region_pixels.py
iiif_validator/tests/region_square.py
iiif_validator/tests/rot_error_random.py
iiif_validator/tests/rot_full_basic.py
iiif_validator/tests/rot_full_non90.py
iiif_validator/tests/rot_mirror.py
iiif_validator/tests/rot_mirror_180.py
iiif_validator/tests/rot_region_basic.py
iiif_validator/tests/rot_region_non90.py
iiif_validator/tests/size_bwh.py
iiif_validator/tests/size_ch.py
iiif_validator/tests/size_error_random.py
iiif_validator/tests/size_nofull.py
iiif_validator/tests/size_noup.py
iiif_validator/tests/size_percent.py
iiif_validator/tests/size_region.py
iiif_validator/tests/size_up.py
iiif_validator/tests/size_wc.py
iiif_validator/tests/size_wh.py
iiif_validator/tests/test.py